GNServer/__init__.py
GNServer/_crt.py
GNServer/_kdc_object.py
GNServer/client/__init__.py
GNServer/client/_client.py
GNServer/client/_client_quic_shell.py
GNServer/server/__init__.py
GNServer/server/_app.py
GNServer/server/_cors_resolver.py
GNServer/server/_datagram_enc.py
GNServer/server/_func_params_validation.py
GNServer/server/_gnserver.py
GNServer/server/_models.py
GNServer/server/_routes.py
gnserver-0.0.100.dist-info/METADATA
gnserver-0.0.100.dist-info/WHEEL
gnserver-0.0.100.dist-info/top_level.txt
gnserver-0.0.100.dist-info/RECORD
