Metadata-Version: 2.4
Name: GNServer
Version: 0.0.100
Summary: GNServer
Home-page: https://github.com/KeyisB/GNServer
Author: KeyisB
Author-email: keyisb.pip@gmail.com
License: GN License v1.0
Classifier: Programming Language :: Python :: 3
Classifier: Operating System :: OS Independent
Requires-Python: >=3.12
Requires-Dist: aioquic
Requires-Dist: anyio
Requires-Dist: gnobjects
Requires-Dist: KeyisBTools
Requires-Dist: aiofiles
Requires-Dist: uvloop
Dynamic: author
Dynamic: author-email
Dynamic: classifier
Dynamic: description
Dynamic: description-content-type
Dynamic: home-page
Dynamic: license
Dynamic: requires-dist
Dynamic: requires-python
Dynamic: summary
